baudot/__init__.py
baudot/core.py
baudot/exceptions.py
baudot/codecs/__init__.py
baudot/codecs/core.py
baudot/codecs/ita1_baudot.py
baudot/codecs/ita2_baudot_murray.py
baudot/handlers/__init__.py
baudot/handlers/core.py
baudot/handlers/hexbytes.py
baudot/handlers/tape.py
baudot-0.1.1.post2.dist-info/LICENSE.txt
baudot-0.1.1.post2.dist-info/METADATA
baudot-0.1.1.post2.dist-info/WHEEL
baudot-0.1.1.post2.dist-info/top_level.txt
baudot-0.1.1.post2.dist-info/RECORD
