Metadata-Version: 2.1
Name: baudot
Version: 0.1.1.post2
Summary: Tools for handling stateful 5-bit encoding
Home-page: https://github.com/xvillaneau/python-baudot
Author: Xavier Villaneau
Author-email: xvillaneau+baudot@gmail.com
License: LGPLv3
Platform: UNKNOWN
Classifier: Development Status :: 4 - Beta
Classifier: License :: OSI Approved :: GNU Lesser General Public License v3 (LGPLv3)
Classifier: Programming Language :: Python :: 3
Classifier: Programming Language :: Python :: 3.6
Classifier: Topic :: Communications
Requires-Python: >=3.6.0
